distributions_for_dsnd
