Metadata-Version: 1.0
Name: distributions-for-dsnd
Version: 0.3
Summary: Gaussian distributions
Home-page: UNKNOWN
Author: Mona Anderssen
Author-email: UNKNOWN
License: UNKNOWN
Platform: UNKNOWN
